{"frames": [

{
	"filename": "btn_audio_off_32x32.png",
	"frame": {"x":2,"y":2,"w":32,"h":32},
	"rotated": false,
	"trimmed": false,
	"spriteSourceSize": {"x":0,"y":0,"w":32,"h":32},
	"sourceSize": {"w":32,"h":32}
},
{
	"filename": "btn_audio_on_32x32.png",
	"frame": {"x":2,"y":36,"w":32,"h":32},
	"rotated": false,
	"trimmed": false,
	"spriteSourceSize": {"x":0,"y":0,"w":32,"h":32},
	"sourceSize": {"w":32,"h":32}
}],
"meta": {
	"app": "http://www.codeandweb.com/texturepacker ",
	"version": "1.0",
	"image": "audio.png",
	"format": "RGBA8888",
	"size": {"w":64,"h":128},
	"scale": "1",
	"smartupdate": "$TexturePacker:SmartUpdate:d967f0c98f06959b244b3e3e79da3098$"
}
}
